swoggle/__init__.py
swoggle/_nbdev.py
swoggle/ai.py
swoggle/core.py
swoggle-0.0.5.dist-info/LICENSE
swoggle-0.0.5.dist-info/METADATA
swoggle-0.0.5.dist-info/WHEEL
swoggle-0.0.5.dist-info/entry_points.txt
swoggle-0.0.5.dist-info/top_level.txt
swoggle-0.0.5.dist-info/RECORD
