Metadata-Version: 2.1
Name: swoggle
Version: 0.0.5
Summary: My implementation of our made up game
Home-page: https://github.com/johnowhitaker/swoggle
Author: Jonathan Whitaker
Author-email: johnowhitaker@gmail.com
License: Apache Software License 2.0
Keywords: swoggle
Platform: UNKNOWN
Classifier: Development Status :: 3 - Alpha
Classifier: Intended Audience :: Developers
Classifier: License :: OSI Approved :: Apache Software License
Classifier: Natural Language :: English
Classifier: Programming Language :: Python :: 3.6
Classifier: Programming Language :: Python :: 3.7
Classifier: Programming Language :: Python :: 3.8
Requires-Python: >=3.6
